gofeatureflag_python_provider/__init__.py
gofeatureflag_python_provider/data_collector_hook.py
gofeatureflag_python_provider/metadata.py
gofeatureflag_python_provider/options.py
gofeatureflag_python_provider/provider.py
gofeatureflag_python_provider/request_data_collector.py
gofeatureflag_python_provider/request_flag_evaluation.py
gofeatureflag_python_provider/response_flag_evaluation.py
gofeatureflag_python_provider-0.4.4.dist-info/METADATA
gofeatureflag_python_provider-0.4.4.dist-info/WHEEL
gofeatureflag_python_provider-0.4.4.dist-info/RECORD
