Metadata-Version: 2.3
Name: gofeatureflag-python-provider
Version: 0.4.4
Summary: GO Feature Flag provider for OpenFeature
License: Apache-2.0
Keywords: feature flags,feature toggles,go-feature-flag,gofeatureflag,openfeature,open-feature
Author: Thomas Poignant
Requires-Python: >=3.9,<4.0
Classifier: License :: OSI Approved :: Apache Software License
Classifier: Programming Language :: Python :: 3
Classifier: Programming Language :: Python :: 3.9
Classifier: Programming Language :: Python :: 3.10
Classifier: Programming Language :: Python :: 3.11
Classifier: Programming Language :: Python :: 3.12
Classifier: Programming Language :: Python :: 3.13
Classifier: Topic :: Software Development :: Libraries :: Application Frameworks
Classifier: Topic :: Software Development :: Libraries :: Python Modules
Requires-Dist: openfeature-sdk (>=0.5.0,<0.9.0)
Requires-Dist: pydantic (>=2.5.2,<3.0.0)
Requires-Dist: pylru (>=1.2.1,<2.0.0)
Requires-Dist: rel (>=0.4.9,<0.5.0)
Requires-Dist: urllib3 (>=2.1.0,<3.0.0)
Requires-Dist: websocket-client (>=1.6.4,<2.0.0)
Project-URL: Bug Tracker, https://github.com/thomaspoignant/go-feature-flag/issues
Project-URL: Documentation, https://github.com/thomaspoignant/go-feature-flag/tree/main/openfeature/providers/python-provider
Project-URL: Homepage, https://gofeatureflag.org
Project-URL: Repository, https://github.com/thomaspoignant/go-feature-flag
Project-URL: Source Code, https://github.com/thomaspoignant/go-feature-flag/tree/main/openfeature/providers/python-provider
